pynterval/__init__.py
pynterval-0.3.dist-info/LICENSE
pynterval-0.3.dist-info/METADATA
pynterval-0.3.dist-info/WHEEL
pynterval-0.3.dist-info/top_level.txt
pynterval-0.3.dist-info/RECORD
